<?xml version="1.0" standalone="yes"?>
<dsUpdateTimes>
  <dtUpdateTimes>
    <TimeDisplay>Day</TimeDisplay>
    <Hours>24</Hours>
  </dtUpdateTimes>
  <dtUpdateTimes>
    <TimeDisplay>2 Days</TimeDisplay>
    <Hours>48</Hours>
  </dtUpdateTimes>
  <dtUpdateTimes>
    <TimeDisplay>5 Days</TimeDisplay>
    <Hours>120</Hours>
  </dtUpdateTimes>
  <dtUpdateTimes>
    <TimeDisplay>7 Days</TimeDisplay>
    <Hours>168</Hours>
  </dtUpdateTimes>
  <dtUpdateTimes>
    <TimeDisplay>10 Days</TimeDisplay>
    <Hours>240</Hours>
  </dtUpdateTimes>
  <dtUpdateTimes>
    <TimeDisplay>2 Weeks</TimeDisplay>
    <Hours>336</Hours>
  </dtUpdateTimes>
  <dtUpdateTimes>
    <TimeDisplay>4 Weeks</TimeDisplay>
    <Hours>672</Hours>
  </dtUpdateTimes>
  <dtUpdateTimes>
    <TimeDisplay>6 Weeks</TimeDisplay>
    <Hours>1008</Hours>
  </dtUpdateTimes>
  <dtUpdateTimes>
    <TimeDisplay>3 Months</TimeDisplay>
    <Hours>2160</Hours>
  </dtUpdateTimes>
  <dtUpdateTimes>
    <TimeDisplay>6 Months</TimeDisplay>
    <Hours>4320</Hours>
  </dtUpdateTimes>
  <dtUpdateTimes>
    <TimeDisplay>Never</TimeDisplay>
    <Hours>0</Hours>
  </dtUpdateTimes>
</dsUpdateTimes>